README.txt
setup.py
mytestlib725.egg-info/PKG-INFO
mytestlib725.egg-info/SOURCES.txt
mytestlib725.egg-info/dependency_links.txt
mytestlib725.egg-info/top_level.txt
mytestlibdir/__init__.py
mytestlibdir/greet.py