Metadata-Version: 1.0
Name: mytestlib725
Version: 1.0.0
Summary: MY Test Library.
Home-page: https://damykouda.org/
Author: TakuyaKouda
Author-email: t-kouda@kbsanhe.co.jp
License: UNKNOWN
Platform: UNKNOWN
